coda_to_end/CodaCl.py
coda_to_end/CodaRegress.py
coda_to_end-0.1.0.dist-info/LICENSE
coda_to_end-0.1.0.dist-info/METADATA
coda_to_end-0.1.0.dist-info/WHEEL
coda_to_end-0.1.0.dist-info/top_level.txt
coda_to_end-0.1.0.dist-info/RECORD
