Metadata-Version: 2.1
Name: coda-to-end
Version: 0.1.0
Summary: A collection of ML algorithms for Compositional Data Analysis
Home-page: https://github.com/sean-lamont/coda-to-end
Author: Sean Lamont
Author-email: sean.a.lamont@outlook.com
License: UNKNOWN
Platform: UNKNOWN
Classifier: Programming Language :: Python :: 3
Classifier: License :: OSI Approved :: BSD License
Classifier: Operating System :: OS Independent
Classifier: Development Status :: 2 - Pre-Alpha
Requires-Dist: numpy
